{
  "page_id": "page_sl0r8oaludumi8xos5qtq1re",
  "raw_word_count": 4608,
  "filtered_word_count": 3330,
  "removed_word_count": 1278,
  "reduction_ratio": 0.277,
  "config": {
    "css_selector": "main",
    "excluded_tags": [
      "header",
      "footer",
      "nav"
    ],
    "excluded_selector": "[class*=\"social\"], [id*=\"social\"], [class*=\"share\"], [id*=\"share\"], [class^=\"ad-\"], [class$=\"-ad\"], [class~=\"ad\"], [id^=\"ad-\"], [id$=\"-ad\"], [id~=\"ad\"], [class*=\"comment\"], [id*=\"comment\"], [class*=\"menu\"], [id*=\"menu\"], [class*=\"breadcrumb\"], [id*=\"breadcrumb\"], [class*=\"form\"], [id*=\"form\"]",
    "confidence": "medium"
  },
  "filtered_at": "2025-11-07T16:59:25.858973"
}