{
  "page_id": "page_qbbvgtt8gylfvllleruzq7hg",
  "raw_word_count": 5034,
  "filtered_word_count": 3676,
  "removed_word_count": 1358,
  "reduction_ratio": 0.27,
  "config": {
    "css_selector": "article, main",
    "excluded_tags": [
      "header",
      "footer",
      "nav",
      "aside"
    ],
    "excluded_selector": "[class^=\"ad-\"], [class$=\"-ad\"], [class~=\"ad\"], [id^=\"ad-\"], [id$=\"-ad\"], [id~=\"ad\"], [class*=\"banner\"], [id*=\"banner\"], [class*=\"menu\"], [id*=\"menu\"], [class*=\"form\"], [id*=\"form\"]",
    "confidence": "high"
  },
  "filtered_at": "2025-11-07T17:00:21.810795"
}