{
  "page_id": "page_lke3uud7qfics8fsiqhf9ysl",
  "raw_word_count": 5767,
  "filtered_word_count": 491,
  "removed_word_count": 5276,
  "reduction_ratio": 0.915,
  "config": {
    "css_selector": "main",
    "excluded_tags": [
      "header",
      "nav",
      "aside"
    ],
    "excluded_selector": "[class*=\"share\"], [id*=\"share\"], [class^=\"ad-\"], [class$=\"-ad\"], [class~=\"ad\"], [id^=\"ad-\"], [id$=\"-ad\"], [id~=\"ad\"], [class*=\"comment\"], [id*=\"comment\"], [class*=\"sidebar\"], [id*=\"sidebar\"], [class*=\"menu\"], [id*=\"menu\"]",
    "confidence": "medium"
  },
  "filtered_at": "2025-11-07T17:00:28.017992"
}