{
  "page_id": "page_mcly6xfnf01wl9svzrtujc50",
  "raw_word_count": 736,
  "filtered_word_count": 157,
  "removed_word_count": 579,
  "reduction_ratio": 0.787,
  "config": {
    "css_selector": "main",
    "excluded_tags": [
      "header",
      "footer",
      "nav"
    ],
    "excluded_selector": "[class^=\"ad-\"], [class$=\"-ad\"], [class~=\"ad\"], [id^=\"ad-\"], [id$=\"-ad\"], [id~=\"ad\"], [class*=\"banner\"], [id*=\"banner\"], [class*=\"sidebar\"], [id*=\"sidebar\"], [class*=\"menu\"], [id*=\"menu\"], [class*=\"form\"], [id*=\"form\"]",
    "confidence": "medium"
  },
  "filtered_at": "2025-11-07T17:00:55.026467"
}