{
  "page_id": "page_gn2ymjakda6jbs5or0xo7utg",
  "raw_word_count": 2244,
  "filtered_word_count": 1874,
  "removed_word_count": 370,
  "reduction_ratio": 0.165,
  "config": {
    "css_selector": "article, main",
    "excluded_tags": [
      "header",
      "footer",
      "nav",
      "aside"
    ],
    "excluded_selector": "[class*=\"share\"], [id*=\"share\"], [class^=\"ad-\"], [class$=\"-ad\"], [class~=\"ad\"], [id^=\"ad-\"], [id$=\"-ad\"], [id~=\"ad\"], [class*=\"menu\"], [id*=\"menu\"], [class*=\"form\"], [id*=\"form\"]",
    "confidence": "high"
  },
  "filtered_at": "2025-11-07T16:57:17.616696"
}