{
  "page_id": "page_pms0d454lloscain6k9qe0oh",
  "raw_word_count": 2275,
  "filtered_word_count": 1654,
  "removed_word_count": 621,
  "reduction_ratio": 0.273,
  "config": {
    "css_selector": "article, main",
    "excluded_tags": [
      "header",
      "footer",
      "nav",
      "aside"
    ],
    "excluded_selector": "[class*=\"social\"], [id*=\"social\"], [class^=\"ad-\"], [class$=\"-ad\"], [class~=\"ad\"], [id^=\"ad-\"], [id$=\"-ad\"], [id~=\"ad\"], [class*=\"sidebar\"], [id*=\"sidebar\"], [class*=\"menu\"], [id*=\"menu\"], [class*=\"breadcrumb\"], [id*=\"breadcrumb\"], [class*=\"form\"], [id*=\"form\"]",
    "confidence": "high"
  },
  "filtered_at": "2025-11-07T17:00:17.704413"
}