{
  "page_id": "page_etx0xn788dghsd8mzr3mddwu",
  "raw_word_count": 3367,
  "filtered_word_count": 2660,
  "removed_word_count": 707,
  "reduction_ratio": 0.21,
  "config": {
    "css_selector": "article, main",
    "excluded_tags": [
      "header",
      "nav",
      "aside"
    ],
    "excluded_selector": "[class^=\"ad-\"], [class$=\"-ad\"], [class~=\"ad\"], [id^=\"ad-\"], [id$=\"-ad\"], [id~=\"ad\"], [class*=\"form\"], [id*=\"form\"]",
    "confidence": "medium"
  },
  "filtered_at": "2025-11-07T16:59:27.925824"
}