{
  "page_id": "page_j9933y2mrui6a8egyv3tavdt",
  "raw_word_count": 3517,
  "filtered_word_count": 2750,
  "removed_word_count": 767,
  "reduction_ratio": 0.218,
  "config": {
    "css_selector": "article, main",
    "excluded_tags": [
      "header",
      "footer",
      "nav",
      "aside"
    ],
    "excluded_selector": "[class^=\"ad-\"], [class$=\"-ad\"], [class~=\"ad\"], [id^=\"ad-\"], [id$=\"-ad\"], [id~=\"ad\"], [class*=\"sidebar\"], [id*=\"sidebar\"], [class*=\"breadcrumb\"], [id*=\"breadcrumb\"]",
    "confidence": "high"
  },
  "filtered_at": "2025-11-07T17:00:46.052784"
}