{
  "domain": "pacificvalleyinsuranceservices.com",
  "total_pages": 1,
  "analyzed_at": "2025-11-07T16:31:20.805763",
  "content_indicators": [
    {
      "selector": "article",
      "count": 0,
      "frequency": 0.0,
      "confidence": "none"
    },
    {
      "selector": "main",
      "count": 0,
      "frequency": 0.0,
      "confidence": "none"
    },
    {
      "selector": "[role=\"main\"]",
      "count": 0,
      "frequency": 0.0,
      "confidence": "none"
    }
  ],
  "non_content_indicators": [
    {
      "tag": "header",
      "count": 0,
      "frequency": 0.0,
      "confidence": "none"
    },
    {
      "tag": "footer",
      "count": 0,
      "frequency": 0.0,
      "confidence": "none"
    },
    {
      "tag": "nav",
      "count": 1,
      "frequency": 1.0,
      "confidence": "high"
    },
    {
      "tag": "aside",
      "count": 0,
      "frequency": 0.0,
      "confidence": "none"
    }
  ],
  "boilerplate_patterns": [
    {
      "pattern": "social",
      "count": 0,
      "frequency": 0.0,
      "confidence": "none"
    },
    {
      "pattern": "share",
      "count": 0,
      "frequency": 0.0,
      "confidence": "none"
    },
    {
      "pattern": "ad",
      "count": 2,
      "frequency": 2.0,
      "confidence": "high"
    },
    {
      "pattern": "ads",
      "count": 0,
      "frequency": 0.0,
      "confidence": "none"
    },
    {
      "pattern": "banner",
      "count": 0,
      "frequency": 0.0,
      "confidence": "none"
    },
    {
      "pattern": "tracker",
      "count": 0,
      "frequency": 0.0,
      "confidence": "none"
    },
    {
      "pattern": "comment",
      "count": 0,
      "frequency": 0.0,
      "confidence": "none"
    },
    {
      "pattern": "sidebar",
      "count": 0,
      "frequency": 0.0,
      "confidence": "none"
    },
    {
      "pattern": "menu",
      "count": 0,
      "frequency": 0.0,
      "confidence": "none"
    },
    {
      "pattern": "breadcrumb",
      "count": 0,
      "frequency": 0.0,
      "confidence": "none"
    },
    {
      "pattern": "form",
      "count": 14,
      "frequency": 14.0,
      "confidence": "high"
    }
  ],
  "top_classes": [
    {
      "class": "MuiGrid-root",
      "count": 19
    },
    {
      "class": "_3a4bHz9Q",
      "count": 11
    },
    {
      "class": "MuiGrid-item",
      "count": 9
    },
    {
      "class": "MuiGrid-grid-xs-12",
      "count": 9
    },
    {
      "class": "rxX3evK0",
      "count": 7
    },
    {
      "class": "_1xesDKxl",
      "count": 6
    },
    {
      "class": "_1W0nIxQ4",
      "count": 6
    },
    {
      "class": "hmEE5dEG",
      "count": 6
    },
    {
      "class": "_3Wj0__qe",
      "count": 6
    },
    {
      "class": "MuiGrid-container",
      "count": 6
    },
    {
      "class": "_1SQCXhDj",
      "count": 5
    },
    {
      "class": "_2kjLHHzo",
      "count": 5
    },
    {
      "class": "_3t9DcoBx",
      "count": 5
    },
    {
      "class": "_3ywAh3wE",
      "count": 5
    },
    {
      "class": "DggARtog",
      "count": 5
    },
    {
      "class": "Cqn11Y4q",
      "count": 5
    },
    {
      "class": "_2ITJo2E7",
      "count": 4
    },
    {
      "class": "MuiFormControl-root",
      "count": 4
    },
    {
      "class": "MuiTextField-root",
      "count": 4
    },
    {
      "class": "MuiFormLabel-root",
      "count": 4
    },
    {
      "class": "MuiInputLabel-root",
      "count": 4
    },
    {
      "class": "MuiInputLabel-formControl",
      "count": 4
    },
    {
      "class": "MuiInputLabel-animated",
      "count": 4
    },
    {
      "class": "MuiInputBase-root",
      "count": 4
    },
    {
      "class": "MuiInput-root",
      "count": 4
    },
    {
      "class": "MuiInputBase-formControl",
      "count": 4
    },
    {
      "class": "MuiInput-formControl",
      "count": 4
    },
    {
      "class": "MuiInputBase-input",
      "count": 4
    },
    {
      "class": "MuiInput-input",
      "count": 4
    },
    {
      "class": "_3b9_S2He",
      "count": 4
    },
    {
      "class": "xM6pFdPG",
      "count": 4
    },
    {
      "class": "d-flex",
      "count": 3
    },
    {
      "class": "d-inline-flex",
      "count": 3
    },
    {
      "class": "relative",
      "count": 3
    },
    {
      "class": "white-space-nowrap",
      "count": 3
    },
    {
      "class": "_8iQG8xgd",
      "count": 3
    },
    {
      "class": "_1dYgj0Ii",
      "count": 3
    },
    {
      "class": "_3SA90bR1",
      "count": 3
    },
    {
      "class": "_1-vQf7iX",
      "count": 3
    },
    {
      "class": "_1XPI7Am9",
      "count": 3
    },
    {
      "class": "_3Jru4OxD",
      "count": 3
    },
    {
      "class": "Z6WnkGfI",
      "count": 3
    },
    {
      "class": "_3ZwofnOy",
      "count": 3
    },
    {
      "class": "_3H4wbIgI",
      "count": 3
    },
    {
      "class": "pzeFFPxz",
      "count": 3
    },
    {
      "class": "_22l71YXw",
      "count": 3
    },
    {
      "class": "Z34jC7sm",
      "count": 3
    },
    {
      "class": "fade-in",
      "count": 2
    },
    {
      "class": "_3MLmYe16",
      "count": 2
    },
    {
      "class": "K1cxCYcN",
      "count": 2
    }
  ],
  "top_ids": [
    {
      "id": "4",
      "count": 5
    },
    {
      "id": "3",
      "count": 5
    },
    {
      "id": "false",
      "count": 4
    },
    {
      "id": "palette_variables_styles_1",
      "count": 1
    },
    {
      "id": "UA-229606846-1&quot;&quot;",
      "count": 1
    },
    {
      "id": "${a}",
      "count": 1
    },
    {
      "id": "mi-local_offer",
      "count": 1
    },
    {
      "id": "mi-chevron_right",
      "count": 1
    },
    {
      "id": "mi-construction",
      "count": 1
    },
    {
      "id": "mi-arrow_circle_right-outlined",
      "count": 1
    },
    {
      "id": "fa-car-side",
      "count": 1
    },
    {
      "id": "mi-laptop-outlined",
      "count": 1
    },
    {
      "id": "mi-lightbulb-outlined",
      "count": 1
    },
    {
      "id": "mi-cabin",
      "count": 1
    },
    {
      "id": "mi-home",
      "count": 1
    },
    {
      "id": "mi-person",
      "count": 1
    },
    {
      "id": "mi-phone",
      "count": 1
    },
    {
      "id": "fa-money-check-dollar",
      "count": 1
    },
    {
      "id": "mi-call-outlined",
      "count": 1
    },
    {
      "id": "mi-message",
      "count": 1
    },
    {
      "id": "fa-message",
      "count": 1
    },
    {
      "id": "mi-handshake-outlined",
      "count": 1
    },
    {
      "id": "mi-calendar_month-outlined",
      "count": 1
    },
    {
      "id": "fa-scissors",
      "count": 1
    },
    {
      "id": "mi-cookie",
      "count": 1
    },
    {
      "id": "mi-battery_charging_full-outlined",
      "count": 1
    },
    {
      "id": "mi-directions_car-outlined",
      "count": 1
    },
    {
      "id": "mi-fire_truck",
      "count": 1
    },
    {
      "id": "mi-call",
      "count": 1
    },
    {
      "id": "mi-health_and_safety-outlined",
      "count": 1
    }
  ],
  "recommendations": {
    "excluded_tags": [
      "nav"
    ],
    "css_selector": null,
    "excluded_selector": "[class^=\"ad-\"], [class$=\"-ad\"], [class~=\"ad\"], [id^=\"ad-\"], [id$=\"-ad\"], [id~=\"ad\"], [class*=\"form\"], [id*=\"form\"]",
    "pruning_threshold": 0.6,
    "min_word_threshold": 50,
    "confidence_score": "low"
  }
}