{
  "domain": "ramseysolutions.com",
  "total_pages": 4,
  "analyzed_at": "2025-11-07T14:35:34.021563",
  "content_indicators": [
    {
      "selector": "article",
      "count": 16,
      "frequency": 4.0,
      "confidence": "high"
    },
    {
      "selector": "main",
      "count": 4,
      "frequency": 1.0,
      "confidence": "high"
    },
    {
      "selector": "[role=\"main\"]",
      "count": 4,
      "frequency": 1.0,
      "confidence": "high"
    }
  ],
  "non_content_indicators": [
    {
      "tag": "header",
      "count": 20,
      "frequency": 5.0,
      "confidence": "high"
    },
    {
      "tag": "footer",
      "count": 20,
      "frequency": 5.0,
      "confidence": "high"
    },
    {
      "tag": "nav",
      "count": 4,
      "frequency": 1.0,
      "confidence": "high"
    },
    {
      "tag": "aside",
      "count": 0,
      "frequency": 0.0,
      "confidence": "none"
    }
  ],
  "boilerplate_patterns": [
    {
      "pattern": "social",
      "count": 35,
      "frequency": 8.75,
      "confidence": "high"
    },
    {
      "pattern": "share",
      "count": 0,
      "frequency": 0.0,
      "confidence": "none"
    },
    {
      "pattern": "ad",
      "count": 197,
      "frequency": 49.25,
      "confidence": "high"
    },
    {
      "pattern": "ads",
      "count": 0,
      "frequency": 0.0,
      "confidence": "none"
    },
    {
      "pattern": "banner",
      "count": 16,
      "frequency": 4.0,
      "confidence": "high"
    },
    {
      "pattern": "tracker",
      "count": 0,
      "frequency": 0.0,
      "confidence": "none"
    },
    {
      "pattern": "comment",
      "count": 0,
      "frequency": 0.0,
      "confidence": "none"
    },
    {
      "pattern": "sidebar",
      "count": 8,
      "frequency": 2.0,
      "confidence": "high"
    },
    {
      "pattern": "menu",
      "count": 2135,
      "frequency": 533.75,
      "confidence": "high"
    },
    {
      "pattern": "breadcrumb",
      "count": 4,
      "frequency": 1.0,
      "confidence": "high"
    },
    {
      "pattern": "form",
      "count": 34,
      "frequency": 8.5,
      "confidence": "high"
    }
  ],
  "top_classes": [
    {
      "class": "rds-Link_toolkit",
      "count": 1522
    },
    {
      "class": "rs-SubmenuMobile-columnItem",
      "count": 879
    },
    {
      "class": "rds-Grid-item_toolkit",
      "count": 595
    },
    {
      "class": "rds-Grid-item--span12_toolkit",
      "count": 582
    },
    {
      "class": "rds-Grid-item--start1_toolkit",
      "count": 580
    },
    {
      "class": "rds-Grid-item--span3@lg_toolkit",
      "count": 576
    },
    {
      "class": "rs-SubmenuTwo--column",
      "count": 576
    },
    {
      "class": "rds-Stack_toolkit",
      "count": 345
    },
    {
      "class": "rds-Text_2",
      "count": 328
    },
    {
      "class": "rds-Text--subdued_2",
      "count": 328
    },
    {
      "class": "rds-Text--bodySmall_2",
      "count": 328
    },
    {
      "class": "u-textAlignLeft",
      "count": 328
    },
    {
      "class": "u-textAlignLeft@sm",
      "count": 328
    },
    {
      "class": "rds-Stack--vertical_toolkit",
      "count": 301
    },
    {
      "class": "rds-Stack--leftVerticalAlignment_toolkit",
      "count": 288
    },
    {
      "class": "rds-Stack--lgSpacing_toolkit",
      "count": 288
    },
    {
      "class": "rds-Button_5",
      "count": 180
    },
    {
      "class": "rds-Button--subtle_5",
      "count": 148
    },
    {
      "class": "rds-Grid-item--start1@lg_toolkit",
      "count": 144
    },
    {
      "class": "rds-Grid-item--start4@lg_toolkit",
      "count": 144
    },
    {
      "class": "rds-Grid-item--start7@lg_toolkit",
      "count": 144
    },
    {
      "class": "rds-Grid-item--start10@lg_toolkit",
      "count": 144
    },
    {
      "class": "rds-Button-icon_5",
      "count": 136
    },
    {
      "class": "rds-Button--iconOnly_5",
      "count": 100
    },
    {
      "class": "rds-Icon_2",
      "count": 100
    },
    {
      "class": "rds-Link-icon_toolkit",
      "count": 92
    },
    {
      "class": "rds-Grid_toolkit",
      "count": 90
    },
    {
      "class": "rds-Link-icon--right_toolkit",
      "count": 88
    },
    {
      "class": "rds-Button--large_5",
      "count": 72
    },
    {
      "class": "rs-SubmenuTwo",
      "count": 72
    },
    {
      "class": "rds-Divider",
      "count": 72
    },
    {
      "class": "rds-Divider--spacingXl",
      "count": 72
    },
    {
      "class": "rds-Grid--gapLarge_toolkit",
      "count": 72
    },
    {
      "class": "rs-SiteFooter-listItem",
      "count": 56
    },
    {
      "class": "rds-Link--small_toolkit",
      "count": 56
    },
    {
      "class": "rs-SiteFooter-link",
      "count": 56
    },
    {
      "class": "u-visuallyHidden",
      "count": 51
    },
    {
      "class": "rds-RichText_1",
      "count": 48
    },
    {
      "class": "rds-Stack--smSpacing_toolkit",
      "count": 41
    },
    {
      "class": "rds-Icon--xsmall_2",
      "count": 40
    },
    {
      "class": "rs-SubmenuMobile",
      "count": 36
    },
    {
      "class": "rs-SubmenuMobile-title",
      "count": 36
    },
    {
      "class": "rs-Submenu-expandContainer",
      "count": 36
    },
    {
      "class": "rs-Submenu-container",
      "count": 36
    },
    {
      "class": "rs-Submenu-innerContainer",
      "count": 36
    },
    {
      "class": "rs-Submenu-containerHeader",
      "count": 36
    },
    {
      "class": "rs-Submenu-closeContainer",
      "count": 36
    },
    {
      "class": "rs-Submenu-containerTitle",
      "count": 36
    },
    {
      "class": "rs-MenuItemMobile",
      "count": 36
    },
    {
      "class": "rs-MenuItem",
      "count": 36
    }
  ],
  "top_ids": [
    {
      "id": "19f6f1cb-2e0c-4881-856a-0b5b31c93c37",
      "count": 24
    },
    {
      "id": "money.the-7-baby-steps",
      "count": 8
    },
    {
      "id": "money.everydollar-budget-app",
      "count": 8
    },
    {
      "id": "money.financial-peace-university",
      "count": 8
    },
    {
      "id": "money.talk-to-a-coach",
      "count": 8
    },
    {
      "id": "money.get-started-assessment",
      "count": 8
    },
    {
      "id": "money.get-out-of-debt",
      "count": 8
    },
    {
      "id": "money.debt-articles",
      "count": 8
    },
    {
      "id": "money.savings-articles",
      "count": 8
    },
    {
      "id": "money.budgeting-articles",
      "count": 8
    },
    {
      "id": "money.see-all-money-resources",
      "count": 8
    },
    {
      "id": "money.debt-snowball-calculator",
      "count": 8
    },
    {
      "id": "money.budget-calculator",
      "count": 8
    },
    {
      "id": "money.the-money-and-relationships-tour",
      "count": 8
    },
    {
      "id": "money.money-and-marriage-getaway",
      "count": 8
    },
    {
      "id": "money.free-live-budgeting-training",
      "count": 8
    },
    {
      "id": "money.see-all-events",
      "count": 8
    },
    {
      "id": "money.ramsey-education-curriculum",
      "count": 8
    },
    {
      "id": "money.college-savings-calculator",
      "count": 8
    },
    {
      "id": "money.tax-services",
      "count": 8
    },
    {
      "id": "money.tax-guide",
      "count": 8
    },
    {
      "id": "money.tax-pro-or-self-file-quiz",
      "count": 8
    },
    {
      "id": "money.see-more-on-money",
      "count": 8
    },
    {
      "id": "investing-and-retirement.smartvestor-pros",
      "count": 8
    },
    {
      "id": "investing-and-retirement.will-and-power-of-attorney",
      "count": 8
    },
    {
      "id": "investing-and-retirement.financial-advisors-101",
      "count": 8
    },
    {
      "id": "investing-and-retirement.estate-planning",
      "count": 8
    },
    {
      "id": "investing-and-retirement.retirement-resources",
      "count": 8
    },
    {
      "id": "investing-and-retirement.retirement-articles",
      "count": 8
    },
    {
      "id": "investing-and-retirement.investing-resources",
      "count": 8
    }
  ],
  "recommendations": {
    "excluded_tags": [
      "header",
      "footer",
      "nav"
    ],
    "css_selector": "article, main, [role=\"main\"]",
    "excluded_selector": "[class*=\"social\"], [id*=\"social\"], [class*=\"ad\"], [id*=\"ad\"], [class*=\"banner\"], [id*=\"banner\"], [class*=\"sidebar\"], [id*=\"sidebar\"], [class*=\"menu\"], [id*=\"menu\"], [class*=\"breadcrumb\"], [id*=\"breadcrumb\"], [class*=\"form\"], [id*=\"form\"]",
    "pruning_threshold": 0.6,
    "min_word_threshold": 50,
    "confidence_score": "high"
  }
}