{
  "domain": "vaned.com",
  "total_pages": 1,
  "analyzed_at": "2025-11-07T16:31:25.819492",
  "content_indicators": [
    {
      "selector": "article",
      "count": 1,
      "frequency": 1.0,
      "confidence": "high"
    },
    {
      "selector": "main",
      "count": 1,
      "frequency": 1.0,
      "confidence": "high"
    },
    {
      "selector": "[role=\"main\"]",
      "count": 1,
      "frequency": 1.0,
      "confidence": "high"
    }
  ],
  "non_content_indicators": [
    {
      "tag": "header",
      "count": 1,
      "frequency": 1.0,
      "confidence": "high"
    },
    {
      "tag": "footer",
      "count": 1,
      "frequency": 1.0,
      "confidence": "high"
    },
    {
      "tag": "nav",
      "count": 4,
      "frequency": 4.0,
      "confidence": "high"
    },
    {
      "tag": "aside",
      "count": 1,
      "frequency": 1.0,
      "confidence": "high"
    }
  ],
  "boilerplate_patterns": [
    {
      "pattern": "social",
      "count": 0,
      "frequency": 0.0,
      "confidence": "none"
    },
    {
      "pattern": "share",
      "count": 0,
      "frequency": 0.0,
      "confidence": "none"
    },
    {
      "pattern": "ad",
      "count": 19,
      "frequency": 19.0,
      "confidence": "high"
    },
    {
      "pattern": "ads",
      "count": 0,
      "frequency": 0.0,
      "confidence": "none"
    },
    {
      "pattern": "banner",
      "count": 0,
      "frequency": 0.0,
      "confidence": "none"
    },
    {
      "pattern": "tracker",
      "count": 0,
      "frequency": 0.0,
      "confidence": "none"
    },
    {
      "pattern": "comment",
      "count": 0,
      "frequency": 0.0,
      "confidence": "none"
    },
    {
      "pattern": "sidebar",
      "count": 1,
      "frequency": 1.0,
      "confidence": "high"
    },
    {
      "pattern": "menu",
      "count": 10,
      "frequency": 10.0,
      "confidence": "high"
    },
    {
      "pattern": "breadcrumb",
      "count": 5,
      "frequency": 5.0,
      "confidence": "high"
    },
    {
      "pattern": "form",
      "count": 26,
      "frequency": 26.0,
      "confidence": "high"
    }
  ],
  "top_classes": [
    {
      "class": "dropdown-item",
      "count": 34
    },
    {
      "class": "clearfix",
      "count": 15
    },
    {
      "class": "row",
      "count": 14
    },
    {
      "class": "with-bord",
      "count": 14
    },
    {
      "class": "col",
      "count": 12
    },
    {
      "class": "field",
      "count": 12
    },
    {
      "class": "field--label-hidden",
      "count": 12
    },
    {
      "class": "d-flex",
      "count": 11
    },
    {
      "class": "field__item",
      "count": 11
    },
    {
      "class": "block",
      "count": 10
    },
    {
      "class": "align-items-center",
      "count": 9
    },
    {
      "class": "region",
      "count": 8
    },
    {
      "class": "nav-item",
      "count": 8
    },
    {
      "class": "nav-link",
      "count": 8
    },
    {
      "class": "content",
      "count": 8
    },
    {
      "class": "mb-3",
      "count": 8
    },
    {
      "class": "list-inline-item",
      "count": 8
    },
    {
      "class": "form-control",
      "count": 7
    },
    {
      "class": "toggle_bar",
      "count": 6
    },
    {
      "class": "visually-hidden",
      "count": 5
    },
    {
      "class": "pe-1",
      "count": 5
    },
    {
      "class": "flex-grow-0",
      "count": 5
    },
    {
      "class": "flex-column",
      "count": 5
    },
    {
      "class": "w-100",
      "count": 5
    },
    {
      "class": "1",
      "count": 5
    },
    {
      "class": "2",
      "count": 5
    },
    {
      "class": "3",
      "count": 5
    },
    {
      "class": "4",
      "count": 5
    },
    {
      "class": "5",
      "count": 5
    },
    {
      "class": "text-formatted",
      "count": 5
    },
    {
      "class": "field--name-body",
      "count": 5
    },
    {
      "class": "field--type-text-with-summary",
      "count": 5
    },
    {
      "class": "col-lg-3",
      "count": 5
    },
    {
      "class": "pb-1",
      "count": 5
    },
    {
      "class": "field--name-field-media-svg",
      "count": 5
    },
    {
      "class": "field--type-three-sixty-svg-image-field",
      "count": 5
    },
    {
      "class": "text-white",
      "count": 5
    },
    {
      "class": "fw-bold",
      "count": 5
    },
    {
      "class": "container-xl",
      "count": 4
    },
    {
      "class": "dropdown",
      "count": 4
    },
    {
      "class": "dropdown-toggle",
      "count": 4
    },
    {
      "class": "dropdown-icon",
      "count": 4
    },
    {
      "class": "ms-lg-1",
      "count": 4
    },
    {
      "class": "dropdown-menu",
      "count": 4
    },
    {
      "class": "6",
      "count": 4
    },
    {
      "class": "btn",
      "count": 4
    },
    {
      "class": "block-block-content",
      "count": 4
    },
    {
      "class": "fab",
      "count": 4
    },
    {
      "class": "fa-xl",
      "count": 4
    },
    {
      "class": "me-3",
      "count": 4
    }
  ],
  "top_ids": [
    {
      "id": "Layer_1",
      "count": 5
    },
    {
      "id": "cjapitag",
      "count": 2
    },
    {
      "id": "+t+",
      "count": 2
    },
    {
      "id": "${t.elId}",
      "count": 2
    },
    {
      "id": "'+o+'",
      "count": 2
    },
    {
      "id": "content",
      "count": 2
    },
    {
      "id": "vwoCode",
      "count": 1
    },
    {
      "id": "D76DA36C8260876960B730B24724D2171|373b1c481f1cc5f09057442441242b43",
      "count": 1
    },
    {
      "id": "+window._vwo_acc_id+",
      "count": 1
    },
    {
      "id": "${t}",
      "count": 1
    },
    {
      "id": "+Jn.accountId+Ti.getUUIDString(d)+",
      "count": 1
    },
    {
      "id": "+a+",
      "count": 1
    },
    {
      "id": "+s+",
      "count": 1
    },
    {
      "id": "_gQ",
      "count": 1
    },
    {
      "id": "+O;if(1==n&&window.VWO._.txtCfg&&(A+=",
      "count": 1
    },
    {
      "id": "+o+",
      "count": 1
    },
    {
      "id": "+d+",
      "count": 1
    },
    {
      "id": "page-wrapper",
      "count": 1
    },
    {
      "id": "navbar-top",
      "count": 1
    },
    {
      "id": "block-tabs-menu",
      "count": 1
    },
    {
      "id": "navbar-main",
      "count": 1
    },
    {
      "id": "cart-mobile",
      "count": 1
    },
    {
      "id": "CollapsingNavbar",
      "count": 1
    },
    {
      "id": "block-realestatenavigation",
      "count": 1
    },
    {
      "id": "block-realestatenavigation-menu",
      "count": 1
    },
    {
      "id": "page",
      "count": 1
    },
    {
      "id": "main-wrapper",
      "count": 1
    },
    {
      "id": "main",
      "count": 1
    },
    {
      "id": "main-content",
      "count": 1
    },
    {
      "id": "block-vaned-content",
      "count": 1
    }
  ],
  "recommendations": {
    "excluded_tags": [
      "header",
      "footer",
      "nav",
      "aside"
    ],
    "css_selector": "article, main, [role=\"main\"]",
    "excluded_selector": "[class^=\"ad-\"], [class$=\"-ad\"], [class~=\"ad\"], [id^=\"ad-\"], [id$=\"-ad\"], [id~=\"ad\"], [class*=\"sidebar\"], [id*=\"sidebar\"], [class*=\"menu\"], [id*=\"menu\"], [class*=\"breadcrumb\"], [id*=\"breadcrumb\"], [class*=\"form\"], [id*=\"form\"]",
    "pruning_threshold": 0.6,
    "min_word_threshold": 50,
    "confidence_score": "high"
  }
}